LICENSE.txt
MANIFEST.in
README.md
setup.py
docs/Makefile
docs/conf.py
docs/constants.rst
docs/index.rst
docs/rarfile.rst
docs/unrar_manual.txt
docs/unrarlib.rst
unrar/__init__.py
unrar/constants.py
unrar/rarfile.py
unrar/unrarlib.py
unrar.egg-info/PKG-INFO
unrar.egg-info/SOURCES.txt
unrar.egg-info/dependency_links.txt
unrar.egg-info/top_level.txt
unrar/tests/__init__.py
unrar/tests/test_corrupted.rar
unrar/tests/test_password.rar
unrar/tests/test_rar.rar
unrar/tests/test_rarfile.py