Metadata-Version: 1.0
Name: unrar
Version: 0.2
Summary: Wrapper for UnRAR library, ctypes-based.
Home-page: http://github.com/matiasb/python-unrar
Author: Matias Bordese
Author-email: mbordese@gmail.com
License: GPL-3
Keywords: unrar ctypes
Platform: UNKNOWN
